Workbook

Sheet Unit Economics
A1: AGENTBOT — Unit Economics & P&L Model
A2: March 2026 · All figures in GBP (£) · Monthly basis
A4: REVENUE PER PLAN | B4: Underground | C4: Collective | D4: Label | E4: Notes
A5: Monthly price (£) | B5: 29 | C5: 69 | D5: 199 | E5: Source: Stripe live catalog
A6: Agents included | B6: 1 | C6: 3 | D6: 100 | E6: "Unlimited" capped at 100 for modeling
A7: RAM per plan | B7: 2GB | C7: 4GB | D7: 8GB
A8: CPU cores per plan | B8: 1 | C8: 2 | D8: 4
A10: VARIABLE COST PER SUBSCRIBER / mo | B10: Underground | C10: Collective | D10: Label
A11: Stripe fee (2.9% + 30p) | B11: =B5*0.029+0.3 -> 1.141 | C11: =C5*0.029+0.3 -> 2.301 | D11: =D5*0.029+0.3 -> 6.071 | E11: Stripe standard UK rate
A12: Render compute (est. per subscriber) | B12: 7 | C12: 15 | D12: 45 | E12: Docker container + share of worker
A13: OpenRouter API pass-through (est.) | B13: 0 | C13: 0 | D13: 0 | E13: BYOK — user pays own AI costs (£0 to us)
A14: Email (Resend, est. per user) | B14: 0.05 | C14: 0.05 | D14: 0.05
A15: Support allocation (est.) | B15: 0 | C15: 1 | D15: 5 | E15: Priority/24-7 support for higher tiers
A16: TOTAL VARIABLE COST / subscriber | B16: =SUM(B11:B15) -> 8.191 | C16: =SUM(C11:C15) -> 18.351 | D16: =SUM(D11:D15) -> 56.121
A17: CONTRIBUTION MARGIN / subscriber | B17: =B5-B16 -> 20.809 | C17: =C5-C16 -> 50.649 | D17: =D5-D16 -> 142.879
A18: Contribution margin % | B18: =IF(B5=0,0,B17/B5) -> 0.71755172 | C18: =IF(C5=0,0,C17/C5) -> 0.73404348 | D18: =IF(D5=0,0,D17/D5) -> 0.71798492

Sheet Monthly P&L
A1: AGENTBOT — Monthly P&L Scenarios
A2: GBP · Scenario modeling: Launch / Month 3 / Month 6
A4: SUBSCRIBER ASSUMPTIONS | B4: Launch (Mo 1) | C4: Month 3 | D4: Month 6
A5: Underground subscribers | B5: 10 | C5: 40 | D5: 120
A6: Collective subscribers | B6: 5 | C6: 25 | D6: 80
A7: Label subscribers | B7: 1 | C7: 5 | D7: 15
A8: Total subscribers | B8: =SUM(B5:B7) -> 16 | C8: =SUM(C5:C7) -> 70 | D8: =SUM(D5:D7) -> 215
A10: REVENUE
A11: Underground revenue | B11: =B5*'Unit Economics'!B5 -> 290 | C11: =C5*'Unit Economics'!B5 -> 1160 | D11: =D5*'Unit Economics'!B5 -> 3480
A12: Collective revenue | B12: =B6*'Unit Economics'!C5 -> 345 | C12: =C6*'Unit Economics'!C5 -> 1725 | D12: =D6*'Unit Economics'!C5 -> 5520
A13: Label revenue | B13: =B7*'Unit Economics'!D5 -> 199 | C13: =C7*'Unit Economics'!D5 -> 995 | D13: =D7*'Unit Economics'!D5 -> 2985
A14: TOTAL GROSS REVENUE | B14: =SUM(B11:B13) -> 834 | C14: =SUM(C11:C13) -> 3880 | D14: =SUM(D11:D13) -> 11985
A16: VARIABLE COSTS
A17: Underground variable costs | B17: =B5*'Unit Economics'!B16 -> 81.91 | C17: =C5*'Unit Economics'!B16 -> 327.64 | D17: =D5*'Unit Economics'!B16 -> 982.92
A18: Collective variable costs | B18: =B6*'Unit Economics'!C16 -> 91.755 | C18: =C6*'Unit Economics'!C16 -> 458.775 | D18: =D6*'Unit Economics'!C16 -> 1468.08
A19: Label variable costs | B19: =B7*'Unit Economics'!D16 -> 56.121 | C19: =C7*'Unit Economics'!D16 -> 280.605 | D19: =D7*'Unit Economics'!D16 -> 841.815
A20: TOTAL VARIABLE COSTS | B20: =SUM(B17:B19) -> 229.786 | C20: =SUM(C17:C19) -> 1067.02 | D20: =SUM(D17:D19) -> 3292.815
A21: CONTRIBUTION MARGIN | B21: =B14-B20 -> 604.214 | C21: =C14-C20 -> 2812.98 | D21: =D14-D20 -> 8692.185
A23: FIXED COSTS (monthly)
A24: Render — Web Service (Starter+) | B24: 7 | C24: 19 | D24: 29
A25: Render — Background Worker | B25: 7 | C25: 19 | D25: 29
A26: Render — PostgreSQL (Basic→Standard) | B26: 7 | C26: 20 | D26: 50
A27: Render — Redis | B27: 0 | C27: 10 | D27: 25
A28: Vercel (Pro) | B28: 20 | C28: 20 | D28: 20
A29: Domain (raveculture.xyz / yr ÷ 12) | B29: 2 | C29: 2 | D29: 2
A30: Resend (email, base plan) | B30: 0 | C30: 0 | D30: 20
A31: Mux (video streaming, est.) | B31: 0 | C31: 20 | D31: 50
A32: GitHub (Team, if needed) | B32: 0 | C32: 4 | D32: 4
A33: Monitoring / error tracking (est.) | B33: 0 | C33: 0 | D33: 29
A34: OpenRouter demo credit top-up | B34: 5 | C34: 10 | D34: 10
A35: TOTAL FIXED COSTS | B35: =SUM(B24:B34) -> 48 | C35: =SUM(C24:C34) -> 124 | D35: =SUM(D24:D34) -> 268
A37: OPERATING PROFIT / LOSS
A38: NET MONTHLY PROFIT / (LOSS) | B38: =B21-B35 -> 556.214 | C38: =C21-C35 -> 2688.98 | D38: =D21-D35 -> 8424.185
A39: Net margin % | B39: =IF(B14=0,0,B38/B14) -> 0.66692326 | C39: =IF(C14=0,0,C38/C14) -> 0.69303608 | D39: =IF(D14=0,0,D38/D14) -> 0.70289403
A40: Annual run-rate | B40: =B38*12 -> 6674.568 | C40: =C38*12 -> 32267.76 | D40: =D38*12 -> 101090.22
A42: BREAKEVEN ANALYSIS
A43: Fixed costs to cover | B43: =B35 -> 48
A44: Avg contribution margin / sub (blended) | B44: =IF(B8=0,0,B21/B8) -> 37.763375
A45: Breakeven subscribers needed | B45: =IF(B44=0,0,ROUNDUP(B43/B44,0)) -> 2
A46: Breakeven MRR needed | B46: =B35+B20 -> 277.786

Sheet Cash Runway
A1: AGENTBOT — 6-Month Cash Runway
B3: Month 1 | C3: Month 2 | D3: Month 3 | E3: Month 4 | F3: Month 5 | G3: Month 6
A4: Starting cash balance | B4: 500 | C4: =B10 -> 1284 | D4: =C10 -> 2784 | E4: =D10 -> 6386 | F4: =E10 -> 12066 | G4: =F10 -> 20376
A5: Total subscribers | B5: 16 | C5: 30 | D5: 70 | E5: 110 | F5: 160 | G5: 215
A6: Blended ARPU (avg rev per user) | B6: 55 | C6: =B6 -> 55 | D6: =B6 -> 55 | E6: =B6 -> 55 | F6: =B6 -> 55 | G6: =B6 -> 55
A7: Monthly revenue | B7: =B5*B6 -> 880 | C7: =C5*C6 -> 1650 | D7: =D5*D6 -> 3850 | E7: =E5*E6 -> 6050 | F7: =F5*F6 -> 8800 | G7: =G5*G6 -> 11825
A8: Monthly total costs (var + fixed) | B8: 96 | C8: 150 | D8: 248 | E8: 370 | F8: 490 | G8: 588
A9: Net cash flow | B9: =B7-B8 -> 784 | C9: =C7-C8 -> 1500 | D9: =D7-D8 -> 3602 | E9: =E7-E8 -> 5680 | F9: =F7-F8 -> 8310 | G9: =G7-G8 -> 11237
A10: ENDING CASH BALANCE | B10: =B4+B9 -> 1284 | C10: =C4+C9 -> 2784 | D10: =D4+D9 -> 6386 | E10: =E4+E9 -> 12066 | F10: =F4+F9 -> 20376 | G10: =G4+G9 -> 31613
